{
  "ID": "chat-01",
  "BG": "res",
  "DataDetail": [
    {
      "OnwerName": "ป้าก้อย",
      "ChatSide": "right",
      "DialogImage": [
        {
          "Image":"image/jane2",
          "ImageSide": "left",
          "Active": false
        }
      ],
      "Content": "อาหารอร่อยมาก"
    },
    {
      "OnwerName": "ป้าก้อย",
      "ChatSide": "right",
      "DialogImage": [
        {
          "Image":"image/jane2",
          "ImageSide": "left",
          "Active": false
        }
      ],
      "Content": "อิ่มมากเลย"
    },
    {
      "OnwerName": "เจน",
      "ChatSide": "left",
      "DialogImage": [
        {
          "Image":"image/jane2",
          "ImageSide": "left",
          "Active": true
        }
      ],
      "Content": "จริงค่ะป้าก้อย"
    },
    {
      "OnwerName": "เจน",
      "ChatSide": "left",
      "DialogImage": [
        {
          "Image":"image/jane2",
          "ImageSide": "left",
          "Active": true
        }
      ],
      "Content": "สมแล้วที่เป็นร้านโปรดที่คุณแม่แนะนำมา"
    },
    {
      "OnwerName": "เจน",
      "ChatSide": "left",
      "DialogImage": [
        {
          "Image":"image/jane2",
          "ImageSide": "left",
          "Active": true
        }
      ],
      "Content": "พี่คะ!"
    },
    {
      "OnwerName": "เจน",
      "ChatSide": "left",
      "DialogImage": [
        {
          "Image":"image/jane2",
          "ImageSide": "left",
          "Active": true
        }
      ],
      "Content": "เช็คบิลด้วยค่ะ"
    },
    {
      "OnwerName": "พนักงาน",
      "ChatSide": "right",
      "DialogImage": [
        {
          "Image": "image/employee",
          "ImageSide": "right",
          "Active": true
        }
      ],
      "Content": "ทั้งหมด 1,765 บาทครับ"
    },
    {
      "OnwerName": "เจน",
      "ChatSide": "left",
      "DialogImage": [
        {
          "Image":"image/jane2",
          "ImageSide": "left",
          "Active": true
        }
      ],
      "Content": "ป้าก้อยคะ"
    },
    {
      "OnwerName": "เจน",
      "ChatSide": "left",
      "DialogImage": [
        {
          "Image":"image/jane2",
          "ImageSide": "left",
          "Active": true
        }
      ],
      "Content": "ข้าวมื้อนี้เดี๋ยวเจนเป็นคนจ่ายเองค่ะ"
    },
    {
      "OnwerName": "เจน",
      "ChatSide": "left",
      "DialogImage": [
        {
          "Image":"image/jane2",
          "ImageSide": "left",
          "Active": true
        }
      ],
      "Content": "มารบกวนป้าก้อยหลายวันแล้วด้วย"
    },
    {
      "OnwerName": "ป้าก้อย",
      "ChatSide": "right",
      "DialogImage": [
        {
          "Image":"image/jane2",
          "ImageSide": "left",
          "Active": false
        }
      ],
      "Content": "ไม่ได้นะหนูเจน"
    },
    {
      "OnwerName": "ป้าก้อย",
      "ChatSide": "right",
      "DialogImage": [
        {
          "Image":"image/jane2",
          "ImageSide": "left",
          "Active": false
        }
      ],
      "Content": "ป้าจ่ายเองลูก"
    },
    {
      "OnwerName": "ป้าก้อย",
      "ChatSide": "right",
      "DialogImage": [
        {
          "Image":"image/jane2",
          "ImageSide": "left",
          "Active": false
        }
      ],
      "Content": "จะให้หลานตัวเท่านี้เลี้ยงได้ยังไง"
    },
    {
      "OnwerName": "ป้าก้อย",
      "ChatSide": "right",
      "DialogImage": [
        {
          "Image":"image/jane2",
          "ImageSide": "left",
          "Active": false
        }
      ],
      "Content": "แสกนจ่ายนะหนุ่ม"
    },
    {
      "OnwerName": "พนักงาน",
      "ChatSide": "right",
      "DialogImage": [
        {
          "Image": "image/employee",
          "ImageSide": "right",
          "Active": true
        }
      ],
      "Content": "รบกวนสแกน QR ที่เคาท์เตอร์นะครับ"
    },
    {
      "OnwerName": "ป้าก้อย",
      "ChatSide": " right",
      "DialogImage": [
        {
          "Image":"image/jane2",
          "ImageSide": "left",
          "Active": false
        }
      ],
      "Content": "ไปกันหนูเจน",
      "LinkType": "dialog",
      "FileName": "story2-19"
    }
  ]
}